weatherusa/weatherusa.py
weatherusa-2.0.0.dist-info/LICENSE
weatherusa-2.0.0.dist-info/METADATA
weatherusa-2.0.0.dist-info/WHEEL
weatherusa-2.0.0.dist-info/top_level.txt
weatherusa-2.0.0.dist-info/RECORD
