Metadata-Version: 2.1
Name: weatherusa
Version: 2.0.0
Summary: A Python package to get Weather data based on US Zip code 
Home-page: https://github.com/soumilshah1995/weatherUSA
Author: Soumil Nitin Shah
Author-email: soushah@my.bridgeport.edu
License: MIT
Platform: UNKNOWN
Classifier: License :: OSI Approved :: MIT License
Classifier: Programming Language :: Python :: 3
Classifier: Programming Language :: Python :: 3.7
Requires-Dist: requests
